sopel_pypi/__init__.py
sopel_pypi/plugin.py
sopel_pypi-0.3.1.dist-info/licenses/COPYING
sopel_pypi-0.3.1.dist-info/METADATA
sopel_pypi-0.3.1.dist-info/WHEEL
sopel_pypi-0.3.1.dist-info/entry_points.txt
sopel_pypi-0.3.1.dist-info/top_level.txt
sopel_pypi-0.3.1.dist-info/RECORD
