Metadata-Version: 2.4
Name: sopel-pypi
Version: 0.3.1
Summary: A Sopel plugin to show information about linked PyPI packages.
Author-email: dgw <dgw@technobabbl.es>
License-Expression: EFL-2.0
Project-URL: Homepage, https://github.com/sopel-irc/sopel-pypi
Project-URL: Bug Tracker, https://github.com/sopel-irc/sopel-pypi/issues
Keywords: sopel,plugin,bot,irc
Platform: Linux x86, x86-64
Classifier: Intended Audience :: Developers
Classifier: Intended Audience :: System Administrators
Classifier: Topic :: Communications :: Chat :: Internet Relay Chat
Requires-Python: <4,>=3.8
License-File: COPYING
Requires-Dist: sopel>=8.0
Requires-Dist: requests
Dynamic: license-file
